pipeadapter/__init__.py
pipeadapter/pipeadapter.py
pipeadapter-0.0.2.dist-info/METADATA
pipeadapter-0.0.2.dist-info/WHEEL
pipeadapter-0.0.2.dist-info/top_level.txt
pipeadapter-0.0.2.dist-info/RECORD
