Metadata-Version: 2.1
Name: pipeadapter
Version: 0.0.2
Summary: Pipedream adapter for eons
Home-page: https://github.com/infrastructure-tech/lib_pipeadapter
Author: Infrastructure Technologies
Author-email: support@infrastructure.tech
Project-URL: Bug Tracker, https://github.com/infrastructure-tech/lib_pipeadapter/issues
Classifier: Programming Language :: Python :: 3
Classifier: License :: OSI Approved :: MIT License
Classifier: Operating System :: OS Independent
Classifier: Development Status :: 3 - Alpha
Requires-Python: >=3.7
Requires-Dist: eons
